retried-9.2.0.dist-info/METADATA
retried-9.2.0.dist-info/WHEEL
retried/__init__.py
retried/__version__.py
retried/aretry.py
retried/retry.py
retried/utils.py
retried-9.2.0.dist-info/RECORD
