Metadata-Version: 2.1
Name: retried
Version: 9.2.0
Summary: A simple and powerful retrying library for Python
Requires-Python: >=3.9
